datasette_cors.py
datasette_cors-1.0.1.dist-info/LICENSE
datasette_cors-1.0.1.dist-info/METADATA
datasette_cors-1.0.1.dist-info/WHEEL
datasette_cors-1.0.1.dist-info/entry_points.txt
datasette_cors-1.0.1.dist-info/top_level.txt
datasette_cors-1.0.1.dist-info/RECORD
