Metadata-Version: 2.1
Name: datasette-cors
Version: 1.0.1
Summary: Datasette plugin for configuring CORS headers
Home-page: https://github.com/simonw/datasette-cors
Author: Simon Willison
License: Apache License, Version 2.0
License-File: LICENSE
Requires-Dist: asgi-cors >=1.0.1
Provides-Extra: test
Requires-Dist: datasette ; extra == 'test'
Requires-Dist: pytest ; extra == 'test'
Requires-Dist: pytest-asyncio ; extra == 'test'
Requires-Dist: httpx ; extra == 'test'
